pyshallow/__init__.py
pyshallow/__main__.py
pyshallow/version.py
pyshallow/gen_evt/__init__.py
pyshallow/gen_evt/_android.py
pyshallow/gen_evt/_osx.py
pyshallow/gen_evt/_win.py
pyshallow/gen_evt/_x11.py
pyshallow-2025.8.23.dist-info/licenses/LICENSE
pyshallow-2025.8.23.dist-info/METADATA
pyshallow-2025.8.23.dist-info/WHEEL
pyshallow-2025.8.23.dist-info/entry_points.txt
pyshallow-2025.8.23.dist-info/top_level.txt
pyshallow-2025.8.23.dist-info/RECORD
